{"creatureDisplayID":0,"description":"$bullet;与盟友协调站位，保证没有|cFF2959D3|Hspell:296688|h[翻滚涟漪]|h|r触碰到艾什凡女勋爵。\r\n$bullet;保证艾什凡女勋爵远离|cFF2959D3|Hspell:296752|h[锋利的珊瑚]|h|r。\r\n$bullet;被|cFF2959D3|Hspell:297333|h[咸水气泡]|h|r标记时，远离其他玩家。\r\n$bullet;与盟友协调使用|cFF2959D3|Hspell:296944|h[艾泽里特弧光]|h|r摧毁|cFF2959D3|Hspell:296555|h[增生珊瑚]|h|r。","filteredByDifficulty":false,"headerType":3,"link":"|cff66bbff|Hjournal:2:20024:14|h[坦克]|h|r","siblingSectionID":20025,"spellID":0,"startsOpen":false,"title":"坦克","uiModelSceneID":0}